foreblocks/__init__.py
foreblocks/att.py
foreblocks/aux.py
foreblocks/core.py
foreblocks/enc_dec.py
foreblocks/fengine.py
foreblocks/pipeline.py
foreblocks/preprocessing.py
foreblocks/quantization.py
foreblocks/utils.py
foreblocks/blocks/__init__.py
foreblocks/blocks/attention.py
foreblocks/blocks/famous.py
foreblocks/blocks/fourier.py
foreblocks/blocks/graph.py
foreblocks/blocks/mamba.py
foreblocks/blocks/multiscale.py
foreblocks/blocks/nha.py
foreblocks/blocks/ode.py
foreblocks/blocks/simple.py
foreblocks/blocks/wavelets.py
foreblocks/darts/__init__.py
foreblocks/darts/darts.py
foreblocks/darts/darts_base.py
foreblocks/darts/darts_metrics.py
foreblocks/darts/darts_plot.py
foreblocks/darts/darts_run.py
foreblocks/pre/__init__.py
foreblocks/pre/ewt.py
foreblocks/pre/filters.py
foreblocks/pre/impute.py
foreblocks/pre/outlier.py
foreblocks/tf/embeddings.py
foreblocks/tf/fed.py
foreblocks/tf/transformer.py
foreblocks/tf/transformer_att.py
foreblocks/tf/transformer_aux.py
foreblocks/tf/transformer_moe.py
foreblocks/third_party/flash_softpick_attn.py
foreblocks/third_party/vsgd.py
foreblocks/tuner/foretuner.py
foreblocks/tuner/foretuner_aux.py
foreblocks/tuner/foretuner_plot.py
foreblocks-0.1.4.dist-info/licenses/LICENSE
foretools/fenginner.py
foretools/vmd.py
foreblocks-0.1.4.dist-info/METADATA
foreblocks-0.1.4.dist-info/WHEEL
foreblocks-0.1.4.dist-info/top_level.txt
foreblocks-0.1.4.dist-info/RECORD
