Metadata-Version: 2.4
Name: foreblocks
Version: 0.1.4
Summary: Modular Time Series Forecasting Library
Author-email: Laio Seman <laioseman@gmail.com>
License: MIT License
Project-URL: Homepage, https://github.com/lseman/foreblocks
Project-URL: Repository, https://github.com/lseman/foreblocks
Keywords: time series,forecasting,deep learning,transformer,lstm,pytorch
Classifier: Development Status :: 3 - Alpha
Classifier: Intended Audience :: Science/Research
Classifier: License :: OSI Approved :: MIT License
Classifier: Programming Language :: Python :: 3
Classifier: Programming Language :: Python :: 3.9
Classifier: Topic :: Scientific/Engineering :: Artificial Intelligence
Requires-Python: >=3.8
License-File: LICENSE
Requires-Dist: torch>=1.12
Requires-Dist: numpy
Requires-Dist: pandas
Requires-Dist: scikit-learn
Requires-Dist: matplotlib
Requires-Dist: PyWavelets
Requires-Dist: pytorch_wavelets
Requires-Dist: wandb
Dynamic: license-file
